alembic/context.pyi
alembic/op.pyi
alembic_stubs-1.0.0.dist-info/LICENSE
alembic_stubs-1.0.0.dist-info/METADATA
alembic_stubs-1.0.0.dist-info/WHEEL
alembic_stubs-1.0.0.dist-info/top_level.txt
alembic_stubs-1.0.0.dist-info/RECORD
