Metadata-Version: 2.1
Name: alembic-stubs
Version: 1.0.0
Summary: Typing Stubs for Alembic
Author-email: Pokoev Aleksei <powerleks@yandex.ru>
Project-URL: Homepage, https://github.com/powerleks/alembic-stubs
Project-URL: Bug Tracker, https://github.com/powerleks/alembic-stubs/issues
Classifier: Programming Language :: Python :: 3
Classifier: License :: OSI Approved :: MIT License
Classifier: Operating System :: OS Independent
Requires-Python: >=3.5
License-File: LICENSE
Requires-Dist: alembic (<1.7.0)
